README.md
setup.py
goodguy_pytools/__init__.py
goodguy_pytools/config.py
goodguy_pytools/go.py
goodguy_pytools/noexcept.py
goodguy_pytools/pool.py
goodguy_pytools/singleton.py
goodguy_pytools.egg-info/PKG-INFO
goodguy_pytools.egg-info/SOURCES.txt
goodguy_pytools.egg-info/dependency_links.txt
goodguy_pytools.egg-info/requires.txt
goodguy_pytools.egg-info/top_level.txt