Metadata-Version: 2.1
Name: goodguy-pytools
Version: 1.0.1
Summary: goodguy python tools
Home-page: https://github.com/goodguy-project/goodguy-pytools
Author: ConanYu
Author-email: c.zing@outlook.com
License: UNKNOWN
Platform: UNKNOWN
Classifier: Programming Language :: Python :: 3.7
Classifier: Programming Language :: Python :: 3.8
Classifier: Programming Language :: Python :: 3.9
Classifier: Programming Language :: Python :: 3.10
Classifier: License :: OSI Approved :: MIT License
Classifier: Operating System :: OS Independent
